chip/CertificateAuthority.py
chip/ChipBleBase.py
chip/ChipBleUtility.py
chip/ChipBluezMgr.py
chip/ChipCommissionableNodeCtrl.py
chip/ChipDeviceCtrl.py
chip/ChipStack.py
chip/FabricAdmin.py
chip/_ChipDeviceCtrl.so
chip/__init__.py
chip/bdx/Bdx.py
chip/bdx/BdxProtocol.py
chip/bdx/BdxTransfer.py
chip/bdx/__init__.py
chip/ble/__init__.py
chip/ble/get_adapters.py
chip/ble/library_handle.py
chip/ble/scan_devices.py
chip/ble/types.py
chip/ble/commissioning/__init__.py
chip/clusters/Attribute.py
chip/clusters/Command.py
chip/clusters/__init__.py
chip/commissioning/__init__.py
chip/commissioning/commissioning_flow_blocks.py
chip/commissioning/pase.py
chip/configuration/__init__.py
chip/credentials/__init__.py
chip/credentials/cert.py
chip/crypto/__init__.py
chip/crypto/fabric.py
chip/crypto/p256keypair.py
chip/discovery/__init__.py
chip/discovery/library_handle.py
chip/discovery/types.py
chip/exceptions/__init__.py
chip/fault_injection/__init__.py
chip/interaction_model/__init__.py
chip/interaction_model/delegate.py
chip/internal/__init__.py
chip/internal/commissioner.py
chip/internal/thread.py
chip/internal/types.py
chip/logging/__init__.py
chip/logging/library_handle.py
chip/logging/types.py
chip/native/__init__.py
chip/setup_payload/__init__.py
chip/setup_payload/setup_payload.py
chip/storage/__init__.py
chip/tracing/__init__.py
chip/utils/CommissioningBuildingBlocks.py
chip/utils/__init__.py
chip/yaml/__init__.py
chip/yaml/data_model_lookup.py
chip/yaml/errors.py
chip/yaml/format_converter.py
chip/yaml/runner.py
home_assistant_chip_core-2025.7.0.dist-info/LICENSE
home_assistant_chip_core-2025.7.0.dist-info/METADATA
home_assistant_chip_core-2025.7.0.dist-info/WHEEL
home_assistant_chip_core-2025.7.0.dist-info/top_level.txt
home_assistant_chip_core-2025.7.0.dist-info/RECORD
