Metadata-Version: 2.1
Name: home-assistant-chip-core
Version: 2025.7.0
Summary: Python-base APIs and tools for CHIP.
Home-page: https://github.com/project-chip/connectedhomeip
License: Apache
Classifier: Intended Audience :: Developers
Classifier: License :: OSI Approved :: Apache Software License
Classifier: Programming Language :: Python :: 3.7
Classifier: Programming Language :: Python :: 3.8
Classifier: Programming Language :: Python :: 3.9
Requires-Python: >=3.7
License-File: LICENSE
Requires-Dist: coloredlogs
Requires-Dist: construct
Requires-Dist: dacite
Requires-Dist: rich
Requires-Dist: pyyaml
Requires-Dist: ipdb
Requires-Dist: deprecation
Requires-Dist: cryptography
Requires-Dist: ecdsa
